LazyPony/__init__.py
LazyPony-0.3.2.dist-info/METADATA
LazyPony-0.3.2.dist-info/WHEEL
LazyPony-0.3.2.dist-info/top_level.txt
LazyPony-0.3.2.dist-info/RECORD
